file_converter/__init__.py
file_converter/convert.py
file_converter/convertly.py
convertly-0.5.2.dist-info/LICENSE
convertly-0.5.2.dist-info/METADATA
convertly-0.5.2.dist-info/WHEEL
convertly-0.5.2.dist-info/entry_points.txt
convertly-0.5.2.dist-info/top_level.txt
convertly-0.5.2.dist-info/RECORD
