Metadata-Version: 2.1
Name: convertly
Version: 0.5.2
Summary: A tool to convert and manipulate media files
Home-page: https://github.com/HudZah/Convertly
Author: HudZah
Author-email: hudzah@hudzah.com
License: MIT
Requires-Python: >=3.6
License-File: LICENSE
Requires-Dist: requests
